{
    "Ar36": {
        "error": 0.00015524638120868297,
        "error_type": "SEM",
        "filter_outliers_dict": {
            "filter_outliers": true,
            "iterations": 1,
            "std_devs": 2
        },
        "fit": "Linear",
        "value": 0.004427620419769663
    },
    "Ar37": {
        "error": 0.009597538236039125,
        "error_type": "SEM",
        "filter_outliers_dict": {
            "filter_outliers": true,
            "iterations": 1,
            "std_devs": 2
        },
        "fit": "Linear",
        "value": 0.09098516033692126
    },
    "Ar38": {
        "error": 0.010580970372130261,
        "error_type": "SEM",
        "filter_outliers_dict": {
            "filter_outliers": true,
            "iterations": 1,
            "std_devs": 2
        },
        "fit": "Linear",
        "value": 0.7520743204940927
    },
    "Ar39": {
        "error": 0.019881294059643395,
        "error_type": "SEM",
        "filter_outliers_dict": {
            "filter_outliers": true,
            "iterations": 1,
            "std_devs": 2
        },
        "fit": "Linear",
        "value": 61.91514474399006
    },
    "Ar40": {
        "error": 0.029765901540704007,
        "error_type": "SEM",
        "filter_outliers_dict": {
            "filter_outliers": true,
            "iterations": 1,
            "std_devs": 2
        },
        "fit": "Linear",
        "value": 70.01067253728678
    }
}